neogidashboard/__init__.py
neogidashboard/combined.py
neogidashboard/console_utilities.py
neogidashboard/ensembles/__init__.py
neogidashboard/ensembles/ensemblebase.py
neogidashboard/ensembles/gui.py
neogidashboard/ensembles/rashg/ensemble_Calib.py
neogidashboard/ensembles/rashg/ensemble_RASHG.py
neogidashboard/ensembles/rashg/ensemble_RASHG_PID.py
neogidashboard/ensembles/stellarnet/ensemble_Stellarnet.py
neogidashboard/utils.py
neogidashboard/visualizer/__init__.py
neogidashboard/visualizer/rashg/__init__.py
neogidashboard/visualizer/rashg/visualizer_calib.py
neogidashboard/visualizer/rashg/visualizer_sixD.py
neogidashboard/visualizer/stellarnet/visualizer_stellarnet.py
neogidashboard/visualizer/visualizer.py
neogidashboard/visualizer/visualizer_base.py
neogidashboard-0.1.4.dist-info/entry_points.txt
neogidashboard-0.1.4.dist-info/WHEEL
neogidashboard-0.1.4.dist-info/METADATA
neogidashboard-0.1.4.dist-info/RECORD
